ophis/__init__.py
ophis/context.py
ophis/database.py
ophis/globals.py
ophis/router.py
ophis/token.py
ophis_py-0.1.0.dist-info/LICENSE
ophis_py-0.1.0.dist-info/METADATA
ophis_py-0.1.0.dist-info/WHEEL
ophis_py-0.1.0.dist-info/top_level.txt
ophis_py-0.1.0.dist-info/RECORD
