Metadata-Version: 2.1
Name: ophis-py
Version: 0.1.0
Summary: Simple Python bindings for AWS applications
Home-page: https://github.com/philcali/ophis-py
Author: Philip Cali
Author-email: philip.cali@gmail.com
License: Apache License 2.0
Classifier: Programming Language :: Python :: 3
Classifier: Programming Language :: Python :: 3.8
Classifier: Programming Language :: Python :: 3.9
Classifier: Programming Language :: Python :: 3.10
Classifier: Programming Language :: Python :: 3.11
Classifier: Programming Language :: Python :: 3.12
Classifier: License :: OSI Approved :: Apache Software License
Classifier: Operating System :: OS Independent
License-File: LICENSE
Requires-Dist: boto3
Requires-Dist: pycryptodome
